cryptarithm/__init__.py
cryptarithm/cryptarithm.py
cryptarithm-0.1.dist-info/METADATA
cryptarithm-0.1.dist-info/WHEEL
cryptarithm-0.1.dist-info/top_level.txt
cryptarithm-0.1.dist-info/RECORD
